{"name":"NPM","slug":"NPM","count":1,"postlist":[{"title":"Node.js 多版本安装及 NPM 镜像配置","uid":"cb51a2133d61232dd118d1d3d5ca5ed4","slug":"BlogRepository/开发工具及环境/Node.js 多版本安装及 NPM 镜像配置","date":"2022-03-10T12:23:09.000Z","updated":"2023-04-20T13:57:44.632Z","comments":true,"path":"api/articles/BlogRepository/开发工具及环境/Node.js 多版本安装及 NPM 镜像配置.json","keywords":null,"cover":"https://cover.png","text":"1. 安装多版本 Node.js1.1 下载首先去官网下载需要的 Node.js 版本，点击其他下载可以下载其他版本的 Node.js 1.2 安装下载完成后先安装低版本的 Node.js，点击 Next 接受，Next 可以按需修改安装路径，Next Next Next 最后安...","link":"","photos":[],"count_time":{"symbolsCount":913,"symbolsTime":"1 mins."},"categories":[{"name":"开发工具及环境","slug":"开发工具及环境","count":11,"path":"api/categories/开发工具及环境.json"}],"tags":[{"name":"NPM","slug":"NPM","count":1,"path":"api/tags/NPM.json"},{"name":"Node.js","slug":"Node-js","count":1,"path":"api/tags/Node-js.json"},{"name":"前端","slug":"前端","count":1,"path":"api/tags/前端.json"}],"author":{"name":"凡","slug":"blog-author","avatar":"https://img-blog.csdnimg.cn/20210313122054101.png","link":"/","description":"","socials":{"github":"https://github.com/Fan223","twitter":"","stackoverflow":"","wechat":"","qq":"","weibo":"https://weibo.com/u/7318914058","zhihu":"https://www.zhihu.com/people/tridiamond","csdn":"https://blog.csdn.net/ACE_U_005A","juejin":"https://juejin.cn/user/1873223546578589","customs":{}}},"feature":false}]}